rcs_storage/__init__.py
rcs_storage/client.py
rcs_storage/scripts/__init__.py
rcs_storage/scripts/main.py
rcs_storage/tests/__init__.py
rcs_storage/tests/fixtures.py
rcs_storage/tests/helpers.py
rcs_storage/tests/test_client.py
rcs_storage/tests/test_scripts_main.py
rcs_storage/tests/mock_api_responses/__init__.py
rcs_storage/tests/mock_api_responses/collections_get.py
rcs_storage/tests/mock_api_responses/collections_list.py
rcs_storage/tests/mock_api_responses/collections_options.py
rcs_storage/tests/mock_api_responses/ingests_list.py
rcs_storage/tests/mock_api_responses/ingests_post.py
rcs_storage/tests/mock_api_responses/reports_usage_by_department.py
rcs_storage/tests/mock_api_responses/storage_products.py
rcs_storage/tests/mock_ingest_upload_files/__init__.py
rcs_storage-0.1.2.dist-info/LICENSE.txt
rcs_storage-0.1.2.dist-info/METADATA
rcs_storage-0.1.2.dist-info/WHEEL
rcs_storage-0.1.2.dist-info/entry_points.txt
rcs_storage-0.1.2.dist-info/top_level.txt
rcs_storage-0.1.2.dist-info/RECORD
